LICENSE.txt
MANIFEST.in
README.md
parsero.py
setup.py
parsero.egg-info/PKG-INFO
parsero.egg-info/SOURCES.txt
parsero.egg-info/dependency_links.txt
parsero.egg-info/entry_points.txt
parsero.egg-info/requires.txt
parsero.egg-info/top_level.txt