Metadata-Version: 1.1
Name: parsero
Version: 0.81
Summary: A Python based Robots.txt audit tool
Home-page: https://github.com/behindthefirewalls/Parsero
Author: Fabian Affolter, C0r3dump, fikoborquez
Author-email: fabian@affolter-engineering.ch, coredump@autistici.org
License: GPLv2+
Keywords: Robots.txt Audit Webserver
Platform: Linux
Classifier: Development Status :: 5 - Production/Stable
Classifier: Environment :: Console
Classifier: Intended Audience :: End Users/Desktop
Classifier: Intended Audience :: System Administrators
Classifier: License :: OSI Approved :: GNU General Public License v2 or later (GPLv2+)
Classifier: Operating System :: POSIX
Classifier: Programming Language :: Python :: 3.3
Classifier: Topic :: Internet :: WWW/HTTP
Classifier: Topic :: Internet :: WWW/HTTP :: Indexing/Search
